LICENSE
MANIFEST.in
README.rst
setup.py
src/geventconnpool/__init__.py
src/geventconnpool/pool.py
src/geventconnpool.egg-info/PKG-INFO
src/geventconnpool.egg-info/SOURCES.txt
src/geventconnpool.egg-info/dependency_links.txt
src/geventconnpool.egg-info/requires.txt
src/geventconnpool.egg-info/top_level.txt