Metadata-Version: 1.1
Name: geventconnpool
Version: 0.2.1
Summary: TCP connection pool for gevent
Home-page: https://github.com/rasky/geventconnpool
Author: Giovanni Bajo
Author-email: rasky@develer.com
License: UNKNOWN
Platform: UNKNOWN
Classifier: Development Status :: 4 - Beta
Classifier: Environment :: No Input/Output (Daemon)
Classifier: Intended Audience :: Developers
Classifier: License :: OSI Approved :: MIT License
Classifier: Natural Language :: English
Classifier: Operating System :: OS Independent
Classifier: Programming Language :: Python :: 2
Classifier: Topic :: Software Development
